our/__init__.py
our/ourer.py
our-25.4.4.dist-info/licenses/LICENSE
our-25.4.4.dist-info/WHEEL
our-25.4.4.dist-info/METADATA
our-25.4.4.dist-info/RECORD
