Metadata-Version: 2.4
Name: our
Version: 25.4.4
Summary: Our, a community link for content, can upload any content, and get.
Author-email: AYMEN||d9c <aymenmw@proton.me>
License-Expression: GPL-3.0-or-later
License-File: LICENSE
Project-URL: Home, https://github.com/kkkik/our
